{
  "data": [
    {
      "id": 28249,
      "title": "Наше счастливое время",
      "kp_id": "274707",
      "imdb_id": "tt0870967",
      "world_art_id": null,
      "type": "movie",
      "add": "2019-06-24 22:32:05",
      "orig_title": "Urideului haengbokhan shigan",
      "year": "2006-09-14",
      "translations": [
        "Любительский (одноголосый закадровый)"
      ],
      "quality": "dvdrip",
      "translation": "Любительский (одноголосый закадровый)",
      "update": "2019-06-25 08:38:08",
      "iframe_src": ""
    },
    {
      "id": 28246,
      "title": "Девушка с маяка",
      "kp_id": "44185",
      "imdb_id": "tt0350805",
      "world_art_id": null,
      "type": "movie",
      "add": "2019-06-24 22:26:56",
      "orig_title": "Devushka s mayaka",
      "year": "1957-08-09",
      "translations": [
        "Оригинальная дорожка"
      ],
      "quality": "webdl",
      "translation": "Оригинальная дорожка",
      "update": "2019-06-25 08:37:58",
      "iframe_src": ""
    },
    {
      "id": 28244,
      "title": "Экстренное торможение",
      "kp_id": "260330",
      "imdb_id": null,
      "world_art_id": null,
      "type": "movie",
      "add": "2019-06-24 22:07:58",
      "orig_title": "Экстренное торможение",
      "year": "2004-01-01",
      "translations": [
        "Оригинальная дорожка"
      ],
      "quality": "dvdrip",
      "translation": "Оригинальная дорожка",
      "update": "2019-06-25 08:36:56",
      "iframe_src": ""
    },
    {
      "id": 28240,
      "title": "Как закалялась сталь",
      "kp_id": "44686",
      "imdb_id": "tt0034932",
      "world_art_id": null,
      "type": "movie",
      "add": "2019-06-24 21:53:17",
      "orig_title": "Kak zakalyalas stal",
      "year": "1942-09-28",
      "translations": [
        "Оригинальная дорожка"
      ],
      "quality": "dvdrip",
      "translation": "Оригинальная дорожка",
      "update": "2019-06-25 08:32:49",
      "iframe_src": ""
    },
    {
      "id": 28239,
      "title": "Кавалер Золотой звезды",
      "kp_id": "44744",
      "imdb_id": "tt0043701",
      "world_art_id": null,
      "type": "movie",
      "add": "2019-06-24 21:49:22",
      "orig_title": "Kavalier zolotoy zvezdy",
      "year": "1951-07-09",
      "translations": [
        "Оригинальная дорожка"
      ],
      "quality": "dvdrip",
      "translation": "Оригинальная дорожка",
      "update": "2019-06-25 08:36:27",
      "iframe_src": ""
    },
    {
      "id": 28235,
      "title": "Концерт фронту",
      "kp_id": "44909",
      "imdb_id": "tt0177891",
      "world_art_id": null,
      "type": "movie",
      "add": "2019-06-24 21:36:49",
      "orig_title": "Kontsert frontu",
      "year": "1942-11-06",
      "translations": [
        "Оригинальная дорожка"
      ],
      "quality": "dvdrip",
      "translation": "Оригинальная дорожка",
      "update": "2019-06-25 08:31:02",
      "iframe_src": ""
    },
    {
      "id": 28234,
      "title": "Земля забвения",
      "kp_id": "506486",
      "imdb_id": "tt1555084",
      "world_art_id": null,
      "type": "movie",
      "add": "2019-06-24 21:33:07",
      "orig_title": "La terre outragée",
      "year": "2011-09-04",
      "translations": [
        "Оригинальная дорожка"
      ],
      "quality": "webdl",
      "translation": "Оригинальная дорожка",
      "update": "2019-06-25 08:33:20",
      "iframe_src": ""
    },
    {
      "id": 28233,
      "title": "Люди не все знают",
      "kp_id": "45168",
      "imdb_id": "tt0314339",
      "world_art_id": null,
      "type": "movie",
      "add": "2019-06-24 21:03:18",
      "orig_title": "Lyudi ne vsyo znayut",
      "year": "1963-11-02",
      "translations": [
        "Оригинальная дорожка"
      ],
      "quality": "vhs",
      "translation": "Оригинальная дорожка",
      "update": "2019-06-25 08:29:51",
      "iframe_src": ""
    },
    {
      "id": 28232,
      "title": "Машенька",
      "kp_id": "46549",
      "imdb_id": "tt0035044",
      "world_art_id": null,
      "type": "movie",
      "add": "2019-06-24 20:57:15",
      "orig_title": "Mashenka",
      "year": "1942-04-10",
      "translations": [
        "Оригинальная дорожка"
      ],
      "quality": "sat",
      "translation": "Оригинальная дорожка",
      "update": "2019-06-25 08:28:15",
      "iframe_src": ""
    },
    {
      "id": 28231,
      "title": "Одна",
      "kp_id": "42730",
      "imdb_id": "tt0022215",
      "world_art_id": null,
      "type": "movie",
      "add": "2019-06-24 20:52:25",
      "orig_title": "Odna",
      "year": "1931-10-10",
      "translations": [
        "Оригинальная дорожка"
      ],
      "quality": "dvdrip",
      "translation": "Оригинальная дорожка",
      "update": "2019-06-25 08:27:26",
      "iframe_src": ""
    },
    {
      "id": 28230,
      "title": "Охота за тенью",
      "kp_id": "427018",
      "imdb_id": null,
      "world_art_id": null,
      "type": "movie",
      "add": "2019-06-24 20:43:17",
      "orig_title": "Охота за тенью",
      "year": "2005-01-01",
      "translations": [
        "Оригинальная дорожка"
      ],
      "quality": "dvdrip",
      "translation": "Оригинальная дорожка",
      "update": "2019-06-25 08:28:23",
      "iframe_src": ""
    },
    {
      "id": 28229,
      "title": "Остров сокровищ",
      "kp_id": "42826",
      "imdb_id": "tt0029356",
      "world_art_id": null,
      "type": "movie",
      "add": "2019-06-24 20:35:42",
      "orig_title": "Ostrov sokrovishch",
      "year": "1938-01-05",
      "translations": [
        "Оригинальная дорожка"
      ],
      "quality": "dvdrip",
      "translation": "Оригинальная дорожка",
      "update": "2019-06-25 08:28:21",
      "iframe_src": ""
    },
    {
      "id": 28228,
      "title": "Последняя прядь",
      "kp_id": "916849",
      "imdb_id": "tt4859520",
      "world_art_id": null,
      "type": "movie",
      "add": "2019-06-24 20:30:18",
      "orig_title": "Poslednyaya pryad",
      "year": "1968-01-01",
      "translations": [
        "Оригинальная дорожка"
      ],
      "quality": "iptv",
      "translation": "Оригинальная дорожка",
      "update": "2019-06-25 08:25:18",
      "iframe_src": ""
    },
    {
      "id": 28227,
      "title": "Заговор обреченных",
      "kp_id": "45206",
      "imdb_id": "tt0043156",
      "world_art_id": null,
      "type": "movie",
      "add": "2019-06-24 20:22:16",
      "orig_title": "Zagovor obrechyonnykh",
      "year": "1950-06-26",
      "translations": [
        "Оригинальная дорожка"
      ],
      "quality": "sat",
      "translation": "Оригинальная дорожка",
      "update": "2019-06-25 08:24:17",
      "iframe_src": ""
    },
    {
      "id": 28226,
      "title": "Ловкачи",
      "kp_id": "45120",
      "imdb_id": "tt0093445",
      "world_art_id": null,
      "type": "movie",
      "add": "2019-06-24 20:17:39",
      "orig_title": "Lovkachi",
      "year": "1988-04-11",
      "translations": [
        "Оригинальная дорожка"
      ],
      "quality": "sat",
      "translation": "Оригинальная дорожка",
      "update": "2019-06-25 08:23:13",
      "iframe_src": ""
    },
    {
      "id": 28220,
      "title": "Насреддин в Бухаре",
      "kp_id": "46346",
      "imdb_id": "tt0036196",
      "world_art_id": null,
      "type": "movie",
      "add": "2019-06-23 22:40:54",
      "orig_title": "Nasreddin v Bukhare",
      "year": "1943-08-02",
      "translations": [
        "Оригинальная дорожка"
      ],
      "quality": "dvdrip",
      "translation": "Оригинальная дорожка",
      "update": "2019-06-25 08:22:06",
      "iframe_src": ""
    },
    {
      "id": 28218,
      "title": "Очарованный странник",
      "kp_id": "436321",
      "imdb_id": "tt5860520",
      "world_art_id": null,
      "type": "movie",
      "add": "2019-06-23 22:34:34",
      "orig_title": "Ocharovannyy strannik",
      "year": "1963-07-09",
      "translations": [
        "Оригинальная дорожка"
      ],
      "quality": "sat",
      "translation": "Оригинальная дорожка",
      "update": "2019-06-25 08:20:07",
      "iframe_src": ""
    },
    {
      "id": 28216,
      "title": "Одинокая женщина с ребенком",
      "kp_id": "433633",
      "imdb_id": null,
      "world_art_id": null,
      "type": "movie",
      "add": "2019-06-23 22:27:58",
      "orig_title": "Одинокая женщина с ребенком",
      "year": "2007-01-01",
      "translations": [
        "Оригинальная дорожка"
      ],
      "quality": "sat",
      "translation": "Оригинальная дорожка",
      "update": "2019-06-25 08:18:47",
      "iframe_src": ""
    },
    {
      "id": 28123,
      "title": "Под маской «Черной кошки»",
      "kp_id": "669367",
      "imdb_id": null,
      "world_art_id": null,
      "type": "movie",
      "add": "2019-06-22 10:40:53",
      "orig_title": "Под маской «Черной кошки»",
      "year": "1990-01-01",
      "translations": [
        "Оригинальная дорожка"
      ],
      "quality": "tv",
      "translation": "Оригинальная дорожка",
      "update": "2019-06-25 08:21:14",
      "iframe_src": ""
    },
    {
      "id": 24204,
      "title": "Испытание верности",
      "kp_id": "42640",
      "imdb_id": "tt0047992",
      "world_art_id": null,
      "type": "movie",
      "add": "2019-04-09 20:46:50",
      "orig_title": "Ispytanie vernosti",
      "year": "1954-12-01",
      "translations": [
        "Оригинальная дорожка"
      ],
      "quality": "hdtv",
      "translation": "Оригинальная дорожка",
      "update": "2019-06-25 08:35:31",
      "iframe_src": ""
    }
  ]
}
