{
  "data": [
    {
      "id": 46055,
      "title": "С Новым годом!",
      "kp_id": "1368989",
      "imdb_id": "tt11615912",
      "world_art_id": null,
      "type": "movie",
      "add": "2020-12-14 09:47:32",
      "orig_title": "Stastny novy rok",
      "year": "2019-12-26",
      "translations": [
        "Полное дублирование"
      ],
      "quality": "webdl",
      "translation": "Полное дублирование",
      "update": "2020-12-14 22:17:07",
      "iframe_src": ""
    },
    {
      "id": 46038,
      "title": "Сэйфти",
      "kp_id": "1304579",
      "imdb_id": "tt10649016",
      "world_art_id": null,
      "type": "movie",
      "add": "2020-12-12 22:37:49",
      "orig_title": "Safety",
      "year": "2020-12-11",
      "translations": [
        "Любительский (многоголосый закадровый) (@MUZOBOZ@)"
      ],
      "quality": "webdl",
      "translation": "Любительский (многоголосый закадровый) (@MUZOBOZ@)",
      "update": "2020-12-13 08:26:13",
      "iframe_src": ""
    },
    {
      "id": 46036,
      "title": "Помочь всем людям",
      "kp_id": "1147237",
      "imdb_id": "tt8161190",
      "world_art_id": null,
      "type": "movie",
      "add": "2020-12-12 22:29:49",
      "orig_title": "To Provide All People",
      "year": "2018-06-28",
      "translations": [
        "Любительский (многоголосый закадровый) (@MUZOBOZ@)"
      ],
      "quality": "webdl",
      "translation": "Любительский (многоголосый закадровый) (@MUZOBOZ@)",
      "update": "2020-12-13 08:21:23",
      "iframe_src": ""
    },
    {
      "id": 46035,
      "title": "Прощай, любовь",
      "kp_id": "1328534",
      "imdb_id": "tt11380884",
      "world_art_id": null,
      "type": "movie",
      "add": "2020-12-12 22:24:22",
      "orig_title": "Farewell Amor",
      "year": "2020-01-25",
      "translations": [
        "Любительский (многоголосый закадровый) (@MUZOBOZ@)"
      ],
      "quality": "webdl",
      "translation": "Любительский (многоголосый закадровый) (@MUZOBOZ@)",
      "update": "2020-12-13 08:12:33",
      "iframe_src": ""
    },
    {
      "id": 46034,
      "title": "История Бонни Паркер",
      "kp_id": "79264",
      "imdb_id": "tt0051430",
      "world_art_id": null,
      "type": "movie",
      "add": "2020-12-12 14:20:05",
      "orig_title": "The Bonnie Parker Story",
      "year": "1958-05-28",
      "translations": [
        "Профессиональный (многоголосый закадровый) (5-й канал СПб)"
      ],
      "quality": "dvdrip",
      "translation": "Профессиональный (многоголосый закадровый) (5-й канал СПб)",
      "update": "2020-12-12 19:45:34",
      "iframe_src": ""
    },
    {
      "id": 46023,
      "title": "Не кликай",
      "kp_id": "1261875",
      "imdb_id": "tt10234450",
      "world_art_id": null,
      "type": "movie",
      "add": "2020-12-11 23:35:26",
      "orig_title": "Don't Click",
      "year": "2020-08-29",
      "translations": [
        "Любительский (многоголосый закадровый) (Синема УС)"
      ],
      "quality": "webdl",
      "translation": "Любительский (многоголосый закадровый) (Синема УС)",
      "update": "2020-12-12 08:55:29",
      "iframe_src": ""
    },
    {
      "id": 46022,
      "title": "Битва в Арденнах 2: Зимняя война",
      "kp_id": "1400981",
      "imdb_id": "tt12631030",
      "world_art_id": null,
      "type": "movie",
      "add": "2020-12-11 23:32:44",
      "orig_title": "Battle of the Bulge: Winter War",
      "year": "2020-11-06",
      "translations": [
        "Любительский (многоголосый закадровый) (@MUZOBOZ@)"
      ],
      "quality": "bd",
      "translation": "Любительский (многоголосый закадровый) (@MUZOBOZ@)",
      "update": "2020-12-13 08:11:37",
      "iframe_src": ""
    },
    {
      "id": 46020,
      "title": "Мы еще молимся",
      "kp_id": "1032073",
      "imdb_id": "tt3408894",
      "world_art_id": null,
      "type": "movie",
      "add": "2020-12-11 23:23:16",
      "orig_title": "We Still Say Grace",
      "year": "2020-01-01",
      "translations": [
        "Любительский (многоголосый закадровый) (@MUZOBOZ@)"
      ],
      "quality": "webdl",
      "translation": "Любительский (многоголосый закадровый) (@MUZOBOZ@)",
      "update": "2020-12-12 08:57:10",
      "iframe_src": ""
    },
    {
      "id": 45999,
      "title": "Ангелы и демоны",
      "kp_id": "194202",
      "imdb_id": "tt0484504",
      "world_art_id": null,
      "type": "movie",
      "add": "2020-12-11 14:53:37",
      "orig_title": "Secrets of Angels, Demons and Masons",
      "year": "2005-10-04",
      "translations": [
        "Профессиональный (многоголосый закадровый)"
      ],
      "quality": "dvdrip",
      "translation": "Профессиональный (многоголосый закадровый)",
      "update": "2020-12-12 11:02:31",
      "iframe_src": ""
    },
    {
      "id": 45905,
      "title": "Фитнэ",
      "kp_id": "773876",
      "imdb_id": "tt2997056",
      "world_art_id": null,
      "type": "movie",
      "add": "2020-12-07 21:24:51",
      "orig_title": "Fitna",
      "year": "1971-01-01",
      "translations": [
        "Оригинальная дорожка"
      ],
      "quality": "webdl",
      "translation": "Оригинальная дорожка",
      "update": "2020-12-15 06:45:02",
      "iframe_src": ""
    },
    {
      "id": 45904,
      "title": "Хроника ереванских дней",
      "kp_id": "188711",
      "imdb_id": "tt0410924",
      "world_art_id": null,
      "type": "movie",
      "add": "2020-12-07 21:18:52",
      "orig_title": "Yerevanyan oreri khronikan",
      "year": "1972-01-01",
      "translations": [
        "Полное дублирование"
      ],
      "quality": "webdl",
      "translation": "Полное дублирование",
      "update": "2020-12-15 06:42:32",
      "iframe_src": ""
    },
    {
      "id": 44755,
      "title": "Глубже!",
      "kp_id": "1199625",
      "imdb_id": "tt11439556",
      "world_art_id": null,
      "type": "movie",
      "add": "2020-10-25 15:37:07",
      "orig_title": "Glubzhe!",
      "year": "2020-10-22",
      "translations": [
        "Оригинальная дорожка"
      ],
      "quality": "webdl",
      "translation": "Оригинальная дорожка",
      "update": "2020-12-12 19:29:20",
      "iframe_src": ""
    },
    {
      "id": 39466,
      "title": "Папина дочка",
      "kp_id": "1118223",
      "imdb_id": "tt8335482",
      "world_art_id": null,
      "type": "movie",
      "add": "2020-04-18 03:44:21",
      "orig_title": "Le prince oublié",
      "year": "2020-02-09",
      "translations": [
        "Любительский (многоголосый закадровый) (@MUZOBOZ@)",
        "Полное дублирование",
        "Полное дублирование (iTunes)"
      ],
      "quality": "webdl",
      "translation": "Любительский (многоголосый закадровый) (@MUZOBOZ@)",
      "update": "2020-12-14 22:03:06",
      "iframe_src": ""
    },
    {
      "id": 28584,
      "title": "Общественная библиотека",
      "kp_id": "806961",
      "imdb_id": "tt3294746",
      "world_art_id": null,
      "type": "movie",
      "add": "2019-07-04 05:41:33",
      "orig_title": "The Public",
      "year": "2018-01-31",
      "translations": [
        "Профессиональный (многоголосый закадровый) (HDrezka Studio)",
        "Профессиональный (многоголосый закадровый) (HDrezka Studio)"
      ],
      "quality": "bd",
      "translation": "Профессиональный (многоголосый закадровый) (HDrezka Studio)",
      "update": "2020-12-14 19:27:03",
      "iframe_src": ""
    },
    {
      "id": 28515,
      "title": "За мечтой",
      "kp_id": "1030353",
      "imdb_id": "tt6483364",
      "world_art_id": null,
      "type": "movie",
      "add": "2019-07-02 20:55:28",
      "orig_title": "Teen Spirit",
      "year": "2018-09-07",
      "translations": [
        "Профессиональный (многоголосый закадровый) (СВ-Студия)",
        "Полное дублирование",
        "Полное дублирование",
        "Профессиональный (многоголосый закадровый) (HDrezka Studio)"
      ],
      "quality": "webdl",
      "translation": "Профессиональный (многоголосый закадровый) (СВ-Студия)",
      "update": "2020-12-14 19:26:23",
      "iframe_src": ""
    },
    {
      "id": 27742,
      "title": "Операция «Колибри»",
      "kp_id": "1048853",
      "imdb_id": "tt6866224",
      "world_art_id": null,
      "type": "movie",
      "add": "2019-06-13 06:14:14",
      "orig_title": "The Hummingbird Project",
      "year": "2018-09-08",
      "translations": [
        "Профессиональный (многоголосый закадровый) (СВ-Студия)",
        "Original (English)",
        "Полное дублирование (iTunes)",
        "Профессиональный (многоголосый закадровый) (HDrezka Studio)"
      ],
      "quality": "bd",
      "translation": "Профессиональный (многоголосый закадровый) (СВ-Студия)",
      "update": "2020-12-14 19:27:18",
      "iframe_src": ""
    },
    {
      "id": 27378,
      "title": "Ветка сирени",
      "kp_id": "266536",
      "imdb_id": "tt0804500",
      "world_art_id": null,
      "type": "movie",
      "add": "2019-06-02 21:33:06",
      "orig_title": "Vetka sireni",
      "year": "2007-12-07",
      "translations": [
        "Оригинальная дорожка",
        "Оригинальная дорожка"
      ],
      "quality": "hdtv",
      "translation": "Оригинальная дорожка",
      "update": "2020-12-14 16:09:34",
      "iframe_src": ""
    },
    {
      "id": 27267,
      "title": "Однажды в Стокгольме",
      "kp_id": "1009498",
      "imdb_id": "tt6474040",
      "world_art_id": null,
      "type": "movie",
      "add": "2019-05-30 20:55:05",
      "orig_title": "Stockholm",
      "year": "2018-04-19",
      "translations": [
        "Полное дублирование",
        "Original (English)",
        "Профессиональный (многоголосый закадровый) (HDrezka Studio)"
      ],
      "quality": "bd",
      "translation": "Полное дублирование",
      "update": "2020-12-14 19:26:10",
      "iframe_src": ""
    },
    {
      "id": 26994,
      "title": "Совершенство",
      "kp_id": "1129042",
      "imdb_id": "tt7772580",
      "world_art_id": null,
      "type": "movie",
      "add": "2019-05-24 21:52:11",
      "orig_title": "The Perfection",
      "year": "2018-09-20",
      "translations": [
        "Профессиональный (многоголосый закадровый) (HDrezka Studio)",
        "Original (English)",
        "Авторский (одноголосый закадровый) (Немахов Юрий)"
      ],
      "quality": "webdl",
      "translation": "Профессиональный (многоголосый закадровый) (HDrezka Studio)",
      "update": "2020-12-14 19:26:38",
      "iframe_src": ""
    },
    {
      "id": 2546,
      "title": "Чёрная река",
      "kp_id": "842168",
      "imdb_id": "tt4793740",
      "world_art_id": null,
      "type": "serial",
      "add": "2018-05-09 04:55:26",
      "orig_title": "Chernaya reka",
      "year": "2015-05-18",
      "translations": [
        "Оригинальная дорожка"
      ],
      "seasons_count": 1,
      "episodes_count": 8,
      "episodes": 8,
      "update": "2018-05-09 07:34:47",
      "iframe_src": ""
    },
    {
      "id": 2537,
      "title": "Ильджимэ",
      "kp_id": "517438",
      "imdb_id": "tt1622764",
      "world_art_id": null,
      "type": "serial",
      "add": "2018-05-06 22:52:01",
      "orig_title": "Iljimae",
      "year": "2008-05-21",
      "translations": [
        "Любительский (одноголосый закадровый) (GREEN TEA)"
      ],
      "seasons_count": 1,
      "episodes_count": 20,
      "episodes": 20,
      "update": "2018-05-08 10:10:51",
      "iframe_src": ""
    },
    {
      "id": 2536,
      "title": "Когда улитка влюблена",
      "kp_id": "1008087",
      "imdb_id": "tt6209406",
      "world_art_id": null,
      "type": "serial",
      "add": "2018-05-06 22:42:46",
      "orig_title": "Ru guo wo niu you ai qing",
      "year": "2016-10-24",
      "translations": [
        "Любительский (двухголосый закадровый) (Sound-Group)"
      ],
      "seasons_count": 1,
      "episodes_count": 21,
      "episodes": 21,
      "update": "2018-05-08 04:22:23",
      "iframe_src": ""
    },
    {
      "id": 2535,
      "title": "Апельсиновый мармелад",
      "kp_id": "906742",
      "imdb_id": "tt4612952",
      "world_art_id": null,
      "type": "serial",
      "add": "2018-05-06 22:33:12",
      "orig_title": "Orenji mamalreideu",
      "year": "2015-05-15",
      "translations": [
        "Любительский (двухголосый закадровый) (GREEN TEA)"
      ],
      "seasons_count": 1,
      "episodes_count": 12,
      "episodes": 12,
      "update": "2018-05-08 04:41:43",
      "iframe_src": ""
    },
    {
      "id": 2534,
      "title": "Старшая сестра",
      "kp_id": "817745",
      "imdb_id": "tt3508578",
      "world_art_id": null,
      "type": "serial",
      "add": "2018-05-06 06:13:28",
      "orig_title": "Starshaya sestra",
      "year": "2013-12-14",
      "translations": [
        "Оригинальная дорожка"
      ],
      "seasons_count": 1,
      "episodes_count": 2,
      "episodes": 2,
      "update": "2018-05-07 06:07:40",
      "iframe_src": ""
    },
    {
      "id": 2533,
      "title": "Ради тебя",
      "kp_id": "789602",
      "imdb_id": null,
      "world_art_id": null,
      "type": "serial",
      "add": "2018-05-06 06:10:24",
      "orig_title": "Ради тебя",
      "year": "2013-08-31",
      "translations": [
        "Оригинальная дорожка"
      ],
      "seasons_count": 1,
      "episodes_count": 2,
      "episodes": 2,
      "update": "2018-05-07 06:10:06",
      "iframe_src": ""
    },
    {
      "id": 2525,
      "title": "Легенда о Тиле",
      "kp_id": "45059",
      "imdb_id": "tt0074784",
      "world_art_id": null,
      "type": "serial",
      "add": "2018-05-06 05:12:15",
      "orig_title": "Legenda o Tile",
      "year": "1977-04-03",
      "translations": [
        "Оригинальная дорожка"
      ],
      "seasons_count": 1,
      "episodes_count": 4,
      "episodes": 4,
      "update": "2018-05-07 07:45:09",
      "iframe_src": ""
    },
    {
      "id": 2510,
      "title": "Пётр Лещенко. Всё, что было...",
      "kp_id": "681879",
      "imdb_id": "tt3571216",
      "world_art_id": null,
      "type": "serial",
      "add": "2018-05-03 14:39:03",
      "orig_title": "Pyotr Leshchenko. Vsyo, chto bylo...",
      "year": "2013-10-14",
      "translations": [
        "Оригинальная дорожка"
      ],
      "seasons_count": 1,
      "episodes_count": 8,
      "episodes": 8,
      "update": "2018-05-09 06:13:11",
      "iframe_src": ""
    },
    {
      "id": 2509,
      "title": "Сын отца народов",
      "kp_id": "710853",
      "imdb_id": "tt3501628",
      "world_art_id": null,
      "type": "serial",
      "add": "2018-05-03 14:32:50",
      "orig_title": "Syn ottsa narodov",
      "year": "2013-08-19",
      "translations": [
        "Оригинальная дорожка"
      ],
      "seasons_count": 1,
      "episodes_count": 12,
      "episodes": 12,
      "update": "2018-05-07 12:57:00",
      "iframe_src": ""
    },
    {
      "id": 2508,
      "title": "Жена офицера",
      "kp_id": "736401",
      "imdb_id": "tt3501614",
      "world_art_id": null,
      "type": "serial",
      "add": "2018-05-03 14:29:56",
      "orig_title": "Zhena ofitsera",
      "year": "2013-02-18",
      "translations": [
        "Оригинальная дорожка"
      ],
      "seasons_count": 1,
      "episodes_count": 8,
      "episodes": 8,
      "update": "2018-05-07 07:35:31",
      "iframe_src": ""
    },
    {
      "id": 2507,
      "title": "Тамарка",
      "kp_id": "893262",
      "imdb_id": "tt4792432",
      "world_art_id": null,
      "type": "serial",
      "add": "2018-05-03 14:25:59",
      "orig_title": "Tamarka",
      "year": "2015-03-06",
      "translations": [
        "Оригинальная дорожка"
      ],
      "seasons_count": 1,
      "episodes_count": 4,
      "episodes": 4,
      "update": "2018-05-07 07:40:34",
      "iframe_src": ""
    },
    {
      "id": 2506,
      "title": "Мир для двоих",
      "kp_id": "829742",
      "imdb_id": "tt4760732",
      "world_art_id": null,
      "type": "serial",
      "add": "2018-05-03 14:23:12",
      "orig_title": "Mir dlya dvoikh",
      "year": "2014-03-01",
      "translations": [
        "Оригинальная дорожка"
      ],
      "seasons_count": 1,
      "episodes_count": 4,
      "episodes": 4,
      "update": "2018-05-04 10:34:40",
      "iframe_src": ""
    },
    {
      "id": 2505,
      "title": "Дождаться любви",
      "kp_id": "820699",
      "imdb_id": "tt3514420",
      "world_art_id": null,
      "type": "serial",
      "add": "2018-05-03 14:17:11",
      "orig_title": "Dozhdatsya lyubvi",
      "year": "2014-02-01",
      "translations": [
        "Оригинальная дорожка"
      ],
      "seasons_count": 1,
      "episodes_count": 2,
      "episodes": 2,
      "update": "2018-05-09 06:02:13",
      "iframe_src": ""
    },
    {
      "id": 2503,
      "title": "Жизненные обстоятельства",
      "kp_id": "839238",
      "imdb_id": null,
      "world_art_id": null,
      "type": "serial",
      "add": "2018-05-03 12:38:08",
      "orig_title": "Жизненные обстоятельства",
      "year": "2014-01-01",
      "translations": [
        "Оригинальная дорожка"
      ],
      "seasons_count": 1,
      "episodes_count": 4,
      "episodes": 4,
      "update": "2018-05-07 16:10:03",
      "iframe_src": ""
    },
    {
      "id": 2502,
      "title": "Отель «Президент»",
      "kp_id": "730935",
      "imdb_id": "tt4083520",
      "world_art_id": null,
      "type": "serial",
      "add": "2018-05-03 12:18:37",
      "orig_title": "Otel 'Prezident'",
      "year": "2013-07-01",
      "translations": [
        "Оригинальная дорожка"
      ],
      "seasons_count": 1,
      "episodes_count": 8,
      "episodes": 8,
      "update": "2018-05-04 10:30:43",
      "iframe_src": ""
    },
    {
      "id": 2500,
      "title": "Брак по завещанию 3. Танцы на углях",
      "kp_id": "807477",
      "imdb_id": "tt4713422",
      "world_art_id": null,
      "type": "serial",
      "add": "2018-05-03 12:13:42",
      "orig_title": "Brak po zaveschaniyu. Tantsi na uglyah",
      "year": "2013-09-28",
      "translations": [
        "Оригинальная дорожка"
      ],
      "seasons_count": 1,
      "episodes_count": 9,
      "episodes": 9,
      "update": "2018-05-04 10:15:53",
      "iframe_src": ""
    },
    {
      "id": 2499,
      "title": "Хуторянин",
      "kp_id": "708703",
      "imdb_id": "tt3329490",
      "world_art_id": null,
      "type": "serial",
      "add": "2018-05-03 12:10:06",
      "orig_title": "Khutoryanin",
      "year": "2013-04-15",
      "translations": [
        "Оригинальная дорожка"
      ],
      "seasons_count": 1,
      "episodes_count": 12,
      "episodes": 12,
      "update": "2018-05-04 10:00:19",
      "iframe_src": ""
    },
    {
      "id": 2498,
      "title": "Стая",
      "kp_id": "466483",
      "imdb_id": null,
      "world_art_id": null,
      "type": "serial",
      "add": "2018-05-03 08:21:50",
      "orig_title": "Стая",
      "year": "2005-01-01",
      "translations": [
        "Оригинальная дорожка"
      ],
      "seasons_count": 1,
      "episodes_count": 2,
      "episodes": 2,
      "update": "2018-05-04 07:28:51",
      "iframe_src": ""
    },
    {
      "id": 2316,
      "title": "Рождество в \"Кровавой горе\"",
      "kp_id": null,
      "imdb_id": "tt7704636",
      "world_art_id": null,
      "type": "serial",
      "add": "2018-03-31 22:33:58",
      "orig_title": "Jul i Blodfjell",
      "year": "2017-12-01",
      "translations": [
        "Профессиональный (двухголосый закадровый) (ViruseProject)"
      ],
      "seasons_count": 1,
      "episodes_count": 24,
      "episodes": 24,
      "update": "2018-05-06 21:31:01",
      "iframe_src": ""
    },
    {
      "id": 1377,
      "title": "Круговорот",
      "kp_id": "986677",
      "imdb_id": null,
      "world_art_id": null,
      "type": "serial",
      "add": "2017-07-07 09:27:36",
      "orig_title": "Круговорот",
      "year": "2017-03-13",
      "translations": [
        "Оригинальная дорожка"
      ],
      "seasons_count": 1,
      "episodes_count": 20,
      "episodes": 20,
      "update": "2018-05-08 14:12:41",
      "iframe_src": ""
    },
    {
      "id": 7662,
      "title": "Комната",
      "kp_id": "38653",
      "imdb_id": "tt0368226",
      "world_art_id": null,
      "type": "movie",
      "add": "2016-11-27 12:45:28",
      "orig_title": "The Room",
      "year": "2003-06-27",
      "translations": [
        "Любительский (одноголосый закадровый)",
        "Original (English)",
        "Профессиональный (многоголосый закадровый) (HDrezka Studio)"
      ],
      "quality": "bd",
      "translation": "Любительский (одноголосый закадровый)",
      "update": "2020-12-14 19:30:28",
      "iframe_src": ""
    }
  ]
}
